spatialdata/__init__.py
spatialdata/__main__.py
spatialdata/_docs.py
spatialdata/_logging.py
spatialdata/_types.py
spatialdata/_utils.py
spatialdata/config.py
spatialdata/datasets.py
spatialdata/testing.py
spatialdata/_bridges/__init__.py
spatialdata/_core/__init__.py
spatialdata/_core/_deepcopy.py
spatialdata/_core/_elements.py
spatialdata/_core/_utils.py
spatialdata/_core/centroids.py
spatialdata/_core/concatenate.py
spatialdata/_core/data_extent.py
spatialdata/_core/spatialdata.py
spatialdata/_core/validation.py
spatialdata/_core/operations/__init__.py
spatialdata/_core/operations/_utils.py
spatialdata/_core/operations/aggregate.py
spatialdata/_core/operations/map.py
spatialdata/_core/operations/rasterize.py
spatialdata/_core/operations/rasterize_bins.py
spatialdata/_core/operations/transform.py
spatialdata/_core/operations/vectorize.py
spatialdata/_core/query/__init__.py
spatialdata/_core/query/_utils.py
spatialdata/_core/query/relational_query.py
spatialdata/_core/query/spatial_query.py
spatialdata/_io/__init__.py
spatialdata/_io/_utils.py
spatialdata/_io/format.py
spatialdata/_io/io_points.py
spatialdata/_io/io_raster.py
spatialdata/_io/io_shapes.py
spatialdata/_io/io_table.py
spatialdata/_io/io_zarr.py
spatialdata/dataloader/__init__.py
spatialdata/dataloader/datasets.py
spatialdata/io/__init__.py
spatialdata/models/__init__.py
spatialdata/models/_accessor.py
spatialdata/models/_utils.py
spatialdata/models/models.py
spatialdata/transformations/__init__.py
spatialdata/transformations/_utils.py
spatialdata/transformations/operations.py
spatialdata/transformations/transformations.py
spatialdata/transformations/ngff/__init__.py
spatialdata/transformations/ngff/_utils.py
spatialdata/transformations/ngff/ngff_coordinate_system.py
spatialdata/transformations/ngff/ngff_transformations.py
spatialdata-0.7.1.post1.dist-info/METADATA
spatialdata-0.7.1.post1.dist-info/WHEEL
spatialdata-0.7.1.post1.dist-info/licenses/LICENSE
spatialdata-0.7.1.post1.dist-info/RECORD
